amdirt/__init__.py
amdirt/cli.py
amdirt/assets/__init__.py
amdirt/assets/tables.json
amdirt/autofill/__init__.py
amdirt/convert/__init__.py
amdirt/core/__init__.py
amdirt/core/diff.py
amdirt/core/ena.py
amdirt/download/__init__.py
amdirt/merge/__init__.py
amdirt/validate/__init__.py
amdirt/validate/exceptions.py
amdirt/validate/application/__init__.py
amdirt/validate/domain/__init__.py
amdirt/viewer/__init__.py
amdirt/viewer/streamlit.py
amdirt-1.6.5.dist-info/LICENSE
amdirt-1.6.5.dist-info/METADATA
amdirt-1.6.5.dist-info/WHEEL
amdirt-1.6.5.dist-info/entry_points.txt
amdirt-1.6.5.dist-info/top_level.txt
amdirt-1.6.5.dist-info/RECORD
