Metadata-Version: 2.1
Name: amdirt
Version: 1.6.5
Summary: amdirt: AncientMetagenomeDir Toolkit
Home-page: https://github.com/SPAAM-community/amdirt
License: GNU-GPLv3
Requires-Python: >=3.9
License-File: LICENSE
Requires-Dist: click
Requires-Dist: pandas
Requires-Dist: tabulate
Requires-Dist: jsonschema
Requires-Dist: rich
Requires-Dist: streamlit <=1.35.0
Requires-Dist: streamlit-aggrid
Requires-Dist: numpy
Requires-Dist: requests
Requires-Dist: colorlog
